homelink/__init__.py
homelink/mqtt_provider.py
homelink/mqtt_util.py
homelink/provider.py
homelink/settings.py
homelink/auth/abstract_auth.py
homelink/auth/aws_srp.py
homelink/auth/srp_auth.py
homelink/model/__init__.py
homelink/model/button.py
homelink/model/device.py
homelink/samples/__init__.py
homelink/samples/mqtt_sample.py
homelink_integration_api-0.0.1.dist-info/licenses/LICENSE
homelink_integration_api-0.0.1.dist-info/METADATA
homelink_integration_api-0.0.1.dist-info/WHEEL
homelink_integration_api-0.0.1.dist-info/top_level.txt
homelink_integration_api-0.0.1.dist-info/RECORD
