Metadata-Version: 2.4
Name: homelink-integration-api
Version: 0.0.1
Summary: API to interact with Homelink cloud for MQTT-enabled smart home platforms
Author-email: Nicholas Aelick <niaexa@syntronic.com>, Ryan Jones <ryan.jones@gentex.com>, Evgeniy Burbyga <evbuxa@syntronic.com>
Project-URL: Homepage, https://www.homelink.com/
Project-URL: Issues, https://www.homelink.com/support
Classifier: Programming Language :: Python :: 3
Classifier: License :: OSI Approved :: MIT License
Classifier: Operating System :: OS Independent
Requires-Python: >=3.12
License-File: LICENSE
Requires-Dist: python-decouple>=3.8
Requires-Dist: boto3
Dynamic: license-file
